odoo/addons/account_refund_early_payment_discount/README.rst
odoo/addons/account_refund_early_payment_discount/__init__.py
odoo/addons/account_refund_early_payment_discount/__manifest__.py
odoo/addons/account_refund_early_payment_discount/i18n/account_refund_early_payment_discount.pot
odoo/addons/account_refund_early_payment_discount/i18n/it.po
odoo/addons/account_refund_early_payment_discount/models/__init__.py
odoo/addons/account_refund_early_payment_discount/models/account_move.py
odoo/addons/account_refund_early_payment_discount/readme/CONTRIBUTORS.md
odoo/addons/account_refund_early_payment_discount/readme/DESCRIPTION.md
odoo/addons/account_refund_early_payment_discount/static/description/icon.png
odoo/addons/account_refund_early_payment_discount/static/description/index.html
odoo/addons/account_refund_early_payment_discount/tests/__init__.py
odoo/addons/account_refund_early_payment_discount/tests/test_refund_early_payment_discount.py
odoo_addon_account_refund_early_payment_discount-18.0.1.0.0.3.dist-info/METADATA
odoo_addon_account_refund_early_payment_discount-18.0.1.0.0.3.dist-info/WHEEL
odoo_addon_account_refund_early_payment_discount-18.0.1.0.0.3.dist-info/top_level.txt
odoo_addon_account_refund_early_payment_discount-18.0.1.0.0.3.dist-info/RECORD
